ryu/__init__.py
ryu/cfg.py
ryu/exception.py
ryu/flags.py
ryu/hooks.py
ryu/log.py
ryu/utils.py
ryu/app/.TestFlow.py.swp
ryu/app/Hub.py
ryu/app/PTDN_Flow.py
ryu/app/TestFlow.py
ryu/app/__init__.py
ryu/app/bmpstation.py
ryu/app/cbench.py
ryu/app/conf_switch_key.py
ryu/app/example_switch_13.py
ryu/app/ofctl_rest.py
ryu/app/rest_conf_switch.py
ryu/app/rest_firewall.py
ryu/app/rest_qos.py
ryu/app/rest_router.py
ryu/app/rest_topology.py
ryu/app/rest_vtep.py
ryu/app/simple_monitor_13.py
ryu/app/simple_switch.py
ryu/app/simple_switch_12.py
ryu/app/simple_switch_13.py
ryu/app/simple_switch_14.py
ryu/app/simple_switch_15.py
ryu/app/simple_switch_igmp.py
ryu/app/simple_switch_igmp_13.py
ryu/app/simple_switch_lacp.py
ryu/app/simple_switch_lacp_13.py
ryu/app/simple_switch_rest_13.py
ryu/app/simple_switch_snort.py
ryu/app/simple_switch_stp.py
ryu/app/simple_switch_stp_13.py
ryu/app/simple_switch_websocket_13.py
ryu/app/ws_topology.py
ryu/app/wsgi.py
ryu/app/gui_topology/__init__.py
ryu/app/gui_topology/gui_topology.py
ryu/app/gui_topology/html/index.html
ryu/app/gui_topology/html/router.svg
ryu/app/gui_topology/html/ryu.topology.css
ryu/app/gui_topology/html/ryu.topology.js
ryu/app/ofctl/__init__.py
ryu/app/ofctl/api.py
ryu/app/ofctl/event.py
ryu/app/ofctl/exception.py
ryu/app/ofctl/service.py
ryu/base/__init__.py
ryu/base/app_manager.py
ryu/cmd/__init__.py
ryu/cmd/manager.py
ryu/cmd/of_config_cli.py
ryu/cmd/ofa_neutron_agent.py
ryu/cmd/rpc_cli.py
ryu/cmd/ryu_base.py
ryu/contrib/__init__.py
ryu/controller/__init__.py
ryu/controller/conf_switch.py
ryu/controller/controller.py
ryu/controller/dpset.py
ryu/controller/event.py
ryu/controller/handler.py
ryu/controller/mac_to_network.py
ryu/controller/mac_to_port.py
ryu/controller/network.py
ryu/controller/ofp_api.py
ryu/controller/ofp_event.py
ryu/controller/ofp_handler.py
ryu/controller/tunnels.py
ryu/lib/__init__.py
ryu/lib/addrconv.py
ryu/lib/addrconv_ptdn.py
ryu/lib/alert.py
ryu/lib/bfdlib.py
ryu/lib/dpid.py
ryu/lib/hub.py
ryu_ptdn-4.34.0.dev3373.dist-info/AUTHORS
ryu_ptdn-4.34.0.dev3373.dist-info/LICENSE
ryu_ptdn-4.34.0.dev3373.dist-info/METADATA
ryu_ptdn-4.34.0.dev3373.dist-info/WHEEL
ryu_ptdn-4.34.0.dev3373.dist-info/entry_points.txt
ryu_ptdn-4.34.0.dev3373.dist-info/top_level.txt
ryu_ptdn-4.34.0.dev3373.dist-info/RECORD
