Metadata-Version: 2.1
Name: ryu-ptdn
Version: 4.34.0.dev3373
Summary: Component-based Software-defined Networking Framework
Home-page: https://ryu-sdn.org
Author: Ryu project team
Author-email: ryu-devel@lists.sourceforge.net
License: Apache License 2.0
Keywords: openflow,openvswitch,openstack
Platform: any
Classifier: Development Status :: 5 - Production/Stable
Classifier: License :: OSI Approved :: Apache Software License
Classifier: Topic :: System :: Networking
Classifier: Natural Language :: English
Classifier: Programming Language :: Python
Classifier: Programming Language :: Python :: 3
Classifier: Programming Language :: Python :: 3.5
Classifier: Programming Language :: Python :: 3.6
Classifier: Programming Language :: Python :: 3.7
Classifier: Programming Language :: Python :: 3.8
Classifier: Programming Language :: Python :: 3.9
Classifier: Operating System :: Unix
License-File: LICENSE
License-File: AUTHORS
Requires-Dist: eventlet (==0.31.1)
Requires-Dist: msgpack (>=0.4.0)
Requires-Dist: netaddr
Requires-Dist: oslo.config (>=2.5.0)
Requires-Dist: ovs (>=2.6.0)
Requires-Dist: packaging (==20.9)
Requires-Dist: routes
Requires-Dist: six (>=1.4.0)
Requires-Dist: tinyrpc (==1.0.4)
Requires-Dist: webob (>=1.2)
